kinbot/__init__.py
kinbot/bfgs.py
kinbot/bond_combinations.py
kinbot/cheminfo.py
kinbot/config_log.py
kinbot/conformers.py
kinbot/constants.py
kinbot/exceptions.py
kinbot/find_motif.py
kinbot/fragments.py
kinbot/frequencies.py
kinbot/geometry.py
kinbot/hindered_rotors.py
kinbot/irc.py
kinbot/kb.py
kinbot/license_message.py
kinbot/mesmer.py
kinbot/mess.py
kinbot/modify_geom.py
kinbot/molpro.py
kinbot/optimize.py
kinbot/orca.py
kinbot/parameters.py
kinbot/pes.py
kinbot/postprocess.py
kinbot/pp_settings.py
kinbot/pp_tables.py
kinbot/qc.py
kinbot/reac_General.py
kinbot/reac_family.py
kinbot/reaction_finder.py
kinbot/reaction_finder_bimol.py
kinbot/reaction_generator.py
kinbot/reader_gauss.py
kinbot/reader_qchem.py
kinbot/stationary_pt.py
kinbot/symmetry.py
kinbot/thread_kinbot.py
kinbot/uncertaintyAnalysis.py
kinbot/utils.py
kinbot/vrc_tst_scan.py
kinbot/vrc_tst_surfaces.py
kinbot/zmatrix.py
kinbot/ase_modules/__init__.py
kinbot/ase_modules/constraints.py
kinbot/ase_modules/calculators/__init__.py
kinbot/ase_modules/calculators/gaussian.py
kinbot/ase_modules/calculators/nn_pes.py
kinbot/ase_modules/calculators/qchem.py
kinbot/ase_modules/io/__init__.py
kinbot/ase_modules/io/formats.py
kinbot/ase_modules/io/gaussian.py
kinbot/ase_modules/io/zmatrix.py
kinbot/reactions/__init__.py
kinbot/reactions/reac_12_shift_S_F.py
kinbot/reactions/reac_12_shift_S_R.py
kinbot/reactions/reac_Cyclic_Ether_Formation.py
kinbot/reactions/reac_Diels_alder_addition.py
kinbot/reactions/reac_HO2_Elimination_from_PeroxyRadical.py
kinbot/reactions/reac_Intra_Diels_alder_R.py
kinbot/reactions/reac_Intra_RH_Add_Endocyclic_F.py
kinbot/reactions/reac_Intra_RH_Add_Endocyclic_R.py
kinbot/reactions/reac_Intra_RH_Add_Exocyclic_F.py
kinbot/reactions/reac_Intra_RH_Add_Exocyclic_R.py
kinbot/reactions/reac_Intra_R_Add_Endocyclic_F.py
kinbot/reactions/reac_Intra_R_Add_ExoTetCyclic_F.py
kinbot/reactions/reac_Intra_R_Add_Exocyclic_F.py
kinbot/reactions/reac_Intra_disproportionation_F.py
kinbot-2.2.4.dist-info/LICENSE
kinbot-2.2.4.dist-info/METADATA
kinbot-2.2.4.dist-info/WHEEL
kinbot-2.2.4.dist-info/entry_points.txt
kinbot-2.2.4.dist-info/top_level.txt
kinbot-2.2.4.dist-info/RECORD
