Metadata-Version: 2.2
Name: kinbot
Version: 2.2.4
Summary: Automated reaction kinetics for gas-phase species
Author-email: Judit Zádor <jzador@sandia.gov>, Ruben Van de Vijver <ruben.vandevijver@ugent.be>, Carles Martí <cmartia@sandia.gov>, Clément Soulié <csoulie@sandia.gov>, Amanda Dewyer <adewyer@sandia.gov>
Maintainer-email: Judit Zádor <jzador@sandia.gov>, Clément Soulié <csoulie@sandia.gov>
License: BSD 3-Clause License
Project-URL: homepage, https://github.com/zadorlab/KinBot
Project-URL: documentation, https://github.com/zadorlab/KinBot/wiki
Classifier: Environment :: Console
Classifier: Intended Audience :: Science/Research
Classifier: Natural Language :: English
Classifier: License :: OSI Approved :: BSD License
Classifier: Operating System :: OS Independent
Classifier: Programming Language :: Python :: 3.10
Classifier: Topic :: Scientific/Engineering :: Chemistry
Requires-Python: >=3.10
License-File: LICENSE
Requires-Dist: numpy>=1.17.0
Requires-Dist: ase<3.22,>=3.19
Requires-Dist: networkx
Requires-Dist: rmsd>=1.5.1
Requires-Dist: sella
Provides-Extra: plot
Requires-Dist: matplotlib; extra == "plot"
Requires-Dist: pyvis; extra == "plot"
Requires-Dist: rdkit; extra == "plot"
